{
    "attribs": {
        "isActive": "yes",
        "isFolder": "no",
        "isTempTrigger": "no",
        "isMultiline": "no",
        "isPerlSlashGOption": "no",
        "isColorizerTrigger": "no",
        "isFilterTrigger": "no",
        "isSoundTrigger": "no",
        "isColorTrigger": "no",
        "isColorTriggerFg": "no",
        "isColorTriggerBg": "no"
    },
    "type": "trigger",
    "name": "Falcon Observe Kill",
    "script": "if not falcon.targetin then\n\tak.deleteFull()\nend\ndisableTrigger(\"Falcon Observe Capture\")\nif ndba and #falcon.areawho > 0 then\n\t--cecho(\"<cyan>\"..ndba.concatand(falcon.areawho)..\" are in \" .. gmcp.Room.Info.area) \n\tsend(\"pt \"..ndba.concatand(falcon.areawho)..\" are in \" .. gmcp.Room.Info.area) \nend\n",
    "triggerType": "0",
    "conditonLineDelta": "0",
    "mStayOpen": "0",
    "mCommand": null,
    "packageName": null,
    "mFgColor": "#ff0000",
    "mBgColor": "#ffff00",
    "mSoundFile": null,
    "colorTriggerFgColor": "#000000",
    "colorTriggerBgColor": "#000000",
    "regexCodeList": "\n\t\t\t\t\t\t\t\t",
    "regexCodePropertyList": "\n\t\t\t\t\t\t\t\t",
    "matches": [
        [
            null,
            "7"
        ]
    ]
}