{
    "attribs": {
        "isActive": "yes",
        "isFolder": "no",
        "isTempTrigger": "no",
        "isMultiline": "yes",
        "isPerlSlashGOption": "no",
        "isColorizerTrigger": "no",
        "isFilterTrigger": "no",
        "isSoundTrigger": "no",
        "isColorTrigger": "no",
        "isColorTriggerFg": "no",
        "isColorTriggerBg": "no"
    },
    "type": "trigger",
    "name": "Pyramid port",
    "script": "local t = mmp.getnums(multimatches[2][2])\nif not t then return end\n\necho\"\\n\"\n\nif #t == 1 then\n\tcecho(\"<red>Porting to <orange_red>\"..mmp.areatabler[getRoomArea(t[1])]..\"<red>.\")\nelse\n\tcecho(\"<red>Might be porting to <orange_red>\"..mmp.areatabler[getRoomArea(t[1])]..\"<red>.\")\nend\t",
    "triggerType": "0",
    "conditonLineDelta": "0",
    "mStayOpen": "0",
    "mCommand": null,
    "packageName": null,
    "mFgColor": "#ff0000",
    "mBgColor": "#ffff00",
    "mSoundFile": null,
    "colorTriggerFgColor": "#000000",
    "colorTriggerBgColor": "#000000",
    "regexCodeList": "\n\t\t\t\t\t\t\t",
    "regexCodePropertyList": "\n\t\t\t\t\t\t\t",
    "matches": [
        [
            "Your hands become a blur as you twist and turn a paradox puzzle pyramid until each side is made up of the same colour, solving the puzzle in mere moments. Suddenly the image of",
            "2"
        ],
        [
            "^Your hands become a blur as you twist and turn a paradox puzzle pyramid until each side is made up of the same colour, solving the puzzle in mere moments. Suddenly the image of (.*) appears in the back of your mind and you feel drawn towards it\\.$",
            "1"
        ]
    ]
}