{
    "attribs": {
        "isActive": "yes",
        "isFolder": "no"
    },
    "type": "script",
    "name": "Opponent Priority Table",
    "packageName": null,
    "script": "--backtrack define\n-------------------------------------------------\n--         Put your Lua functions here.        --\n--                                             --\n-- Note that you can also use external Scripts --\n-------------------------------------------------\nfunction ak.AddedAffReset(affliction)\n   if ocured then\n      for k,v in pairs(ocured) do\n         --display(ocured[k]) \n         if table.contains(ocured[k], affliction) then\n            ocured[k] = nil\n         end   \n      end\n   end\nend\n\nfunction ak.ResetConfirmAff(affliction)\n   if ocured then\n      for k,v in pairs(ocured) do\n\t\t\t\t if type(v) == \"table\" and v[affliction] then\n            v[affliction] = nil  \n\t\t\t\t end \n      end\n   end\nend\n\nocured = ocured or {\n   parseout = {},\n   conversion = {\n       [\"aurum flake\"]      = \"kelp\",\n       [\"piece of kelp\"]    = \"kelp\",\n       [\"lobelia seed\"]     = \"lobelia\",\n       [\"argentum flake\"]   = \"lobelia\",\n       [\"prickly ash bark\"] = \"ash\",\n       [\"stannum flake\"]    = \"ash\",\n       [\"bellwort flower\"]  = \"bellwort\",\n       [\"cuprum flake\"]     = \"bellwort\",\n       [\"goldenseal root\"]  = \"goldenseal\",\n       [\"plumbum flake\"]    = \"goldenseal\",\n       [\"bloodroot leaf\"]   = \"bloodroot\",\n       [\"magnesium chip\"]   = \"bloodroot\",\n       [\"ginseng root\"]     = \"ginseng\",\n       [\"ferrum flake\"]     = \"ginseng\",\n       [\"rage\"]             = \"rage\",\n       [\"hawthorn berry\"]   = \"hawthorn\",\n       [\"calamine crystal\"] = \"hawthorn\",\n       [\"bayberry bark\"]    = \"bayberry\",\n       [\"arsenic pellet\"]   = \"bayberry\"\n   },\n   curemethods = {\n   \"treed\",\n   \"focused\",\n   \"restored\",\n   \"smoked\",\n   \"cureall\",\n   \"applied\",\n   } \n}\n\nfunction ak.resetbacktrack()\nocured = {\n   conversion = {\n       [\"aurum flake\"]      = \"kelp\",\n       [\"piece of kelp\"]    = \"kelp\",\n       [\"lobelia seed\"]     = \"lobelia\",\n       [\"argentum flake\"]   = \"lobelia\",\n       [\"prickly ash bark\"] = \"ash\",\n       [\"stannum flake\"]    = \"ash\",\n       [\"bellwort flower\"]  = \"bellwort\",\n       [\"cuprum flake\"]     = \"bellwort\",\n       [\"goldenseal root\"]  = \"goldenseal\",\n       [\"plumbum flake\"]    = \"goldenseal\",\n       [\"bloodroot leaf\"]   = \"bloodroot\",\n       [\"magnesium chip\"]   = \"bloodroot\",\n       [\"ginseng root\"]     = \"ginseng\",\n       [\"ferrum flake\"]     = \"ginseng\",\n       [\"rage\"]             = \"rage\",\n       [\"hawthorn berry\"]    = \"hawthorn\",\n       [\"calamine crystal\"] = \"hawthorn\",\n       [\"bayberry bark\"]    = \"bayberry\",\n       [\"arsenic pellet\"]   = \"bayberry\"\n   },\n   curemethods = {\n   \"treed\",\n   \"focused\",\n   \"restored\",\n   \"smoked\",\n   \"cureall\",\n   \"applied\",\n   } \n}\nend\n\n",
    "eventHandlerList": null
}