{
    "attribs": {
        "isActive": "yes",
        "isFolder": "no"
    },
    "type": "script",
    "name": "Lyre Queue",
    "packageName": null,
    "script": "function wsys.lyrequeue()\n if wsys.uselyre and not wsys.paused and wsys.bals.b and wsys.bals.e and not wsys.aff.aeon and not wsys.def.lyre and not wsys.timer.lyrewait and not wsys.aff.paralysed and not wsys.tanglecheck() and not wsys.damagedarms() and not wsys.aff.prone then\n  wsys.checkaffs()\n  wsys.lyre()\n end -- if\nend -- func",
    "eventHandlerList": null
}