{
    "attribs": {
        "isActive": "yes",
        "isFolder": "no",
        "isTempTrigger": "no",
        "isMultiline": "no",
        "isPerlSlashGOption": "no",
        "isColorizerTrigger": "no",
        "isFilterTrigger": "no",
        "isSoundTrigger": "no",
        "isColorTrigger": "no",
        "isColorTriggerFg": "no",
        "isColorTriggerBg": "no"
    },
    "type": "trigger",
    "name": "Wildgrowth +",
    "script": "wsys.deffed(\"wildgrowth\")",
    "triggerType": "0",
    "conditonLineDelta": "0",
    "mStayOpen": "0",
    "mCommand": null,
    "packageName": null,
    "mFgColor": "#ff0000",
    "mBgColor": "#ffff00",
    "mSoundFile": null,
    "colorTriggerFgColor": "#000000",
    "colorTriggerBgColor": "#000000",
    "regexCodeList": "\n\t\t\t\t\t\t\t\t\t",
    "regexCodePropertyList": "\n\t\t\t\t\t\t\t\t\t",
    "matches": [
        [
            "You quietly recite an incantation calling on all that is wild and green. As you speak the final syllables, you slowly raise your quarterstaff skywards,",
            "2"
        ],
        [
            "Wild vines already circle your feet.",
            "3"
        ]
    ]
}